streamlit_uploads_library/__init__.py
streamlit_uploads_library/gallery.py
streamlit_uploads_library/library.py
streamlit_uploads_library/uploads.py
streamlit_uploads_library-0.1.4.dist-info/LICENSE
streamlit_uploads_library-0.1.4.dist-info/METADATA
streamlit_uploads_library-0.1.4.dist-info/WHEEL
streamlit_uploads_library-0.1.4.dist-info/top_level.txt
streamlit_uploads_library-0.1.4.dist-info/RECORD
