Metadata-Version: 2.1
Name: streamlit-uploads-library
Version: 0.1.4
Summary: A simple library or gallery for Streamlit made from widgets.
Home-page: https://github.com/hreikin/streamlit-uploads-library
Author: Michael Haslam
Author-email: hreikin@gmail.com
License: MIT
Keywords: streamlit,uploads,library,gallery,widgets
Classifier: Programming Language :: Python :: 3
Classifier: License :: OSI Approved :: MIT License
Classifier: Operating System :: OS Independent
License-File: LICENSE
Requires-Dist: streamlit (>=1.20.0)
Requires-Dist: opsdroid-get-image-size (>=0.2.2)
